1. D-Flip-Flop/srlatch.v
module sr_latch
(
    input s,
    input r,
    output q,
    output notq
);

    nor(q, s, notq);
    nor(notq, r, q);
    
endmodule

1. D-Flip-Flop/dlatch.v
`include "srlatch.v"

module d_latch
(
    input d,
    input e,
    output q,
    output notq
);
    
    wire r; 
    wire s;

    and(s, d, e);
    and(r, ~d, e);

    sr_latch sr_latch(.s(r), .r(s), .q(q), .notq(notq));

endmodule

1. D-Flip-Flop/dflipflop.v
`include "dlatch.v"

module d_flip_flop
(
    input d,
    input e,
    output q,
    output notq
);
    
    wire q_master; 
    wire notq_master;

    wire not_e = ~e;

    d_latch d_latch_master(.d(d), .e(not_e), .q(q_master), .notq(notq_master));

    wire d_slave = q_master;
    wire e_slave = e; 

    d_latch d_latch_slave(.d(d_slave), .e(e_slave), .q(q), .notq(notq));

endmodule

1. D-Flip-Flop/test_dflipflop.v
`timescale 1 ns / 100 ps

module test_d_flip_flop(); /* No inputs, no outputs */

reg d = 1'b1; /* Represents clock, initial value is 0 */
reg e = 1'b0; /* Represents clock, initial value is 0 */

always begin
    #1.32 d = ~d; /* Toggle clock every 1ns */
end

always begin
    #2 e = ~e;
end

wire q; /* For output of tested module */
wire notq; /* For output of tested module */

d_flip_flop d_flip_flop(.d(d), .e(e), .q(q), .notq(notq)); /* Tested module instance */

initial begin
    $dumpvars;      /* Open for dump of signals */
    $display("Test started...");   /* Write to console */
    #16 $finish;    /* Stop simulation after 10ns */
end

endmodule

1. D-Flip-Flop/dump.vcd
$date
	Mon Feb 22 21:16:42 2021
$end
$version
	Icarus Verilog
$end
$timescale
	100ps
$end
$scope module test_d_flip_flop $end
$var wire 1 ! q $end
$var wire 1 " notq $end
$var reg 1 # d $end
$var reg 1 $ e $end
$scope module d_flip_flop $end
$var wire 1 # d $end
$var wire 1 % d_slave $end
$var wire 1 $ e $end
$var wire 1 & e_slave $end
$var wire 1 ' not_e $end
$var wire 1 ( q_master $end
$var wire 1 ! q $end
$var wire 1 ) notq_master $end
$var wire 1 " notq $end
$scope module d_latch_master $end
$var wire 1 # d $end
$var wire 1 ' e $end
$var wire 1 * r $end
$var wire 1 + s $end
$var wire 1 ( q $end
$var wire 1 ) notq $end
$scope module sr_latch $end
$var wire 1 ) notq $end
$var wire 1 ( q $end
$var wire 1 + r $end
$var wire 1 * s $end
$upscope $end
$upscope $end
$scope module d_latch_slave $end
$var wire 1 % d $end
$var wire 1 & e $end
$var wire 1 , r $end
$var wire 1 - s $end
$var wire 1 ! q $end
$var wire 1 " notq $end
$scope module sr_latch $end
$var wire 1 " notq $end
$var wire 1 ! q $end
$var wire 1 - r $end
$var wire 1 , s $end
$upscope $end
$upscope $end
$upscope $end
$upscope $end
$enddefinitions $end
#0
$dumpvars
0-
0,
1+
0*
0)
1(
1'
0&
1%
0$
1#
x"
x!
$end
#13
1)
0%
0(
1*
0+
0#
#20
1"
0*
0!
0'
1,
1&
1$
#26
1#
#39
0#
#40
1*
1'
0,
0&
0$
#52
1%
1(
0)
0*
1+
1#
#60
1!
0+
0"
0'
1-
1&
1$
#65
0#
#78
1#
#80
1+
1'
0-
0&
0$
#91
1)
0%
0(
1*
0+
0#
#100
1"
0*
0!
0'
1,
1&
1$
#104
1#
#117
0#
#120
1*
1'
0,
0&
0$
#130
1%
1(
0)
0*
1+
1#
#140
1!
0+
0"
0'
1-
1&
1$
#143
0#
#156
1#
#160
1+
1'
0-
0&
0$
